deforest/__init__.py
deforest/cleaners.py
deforest/constant.py
deforest/deforest.py
deforest/filecleaner.py
deforest/filecreator.py
deforest/tags.py
deforest/tests/__init__.py
deforest/tests/test_cf_cleaner.py
deforest/tests/test_default_cleaner.py
deforest/tests/test_filecreator.py
deforest/tests/test_ignore_cleaner.py
deforest/tests/test_importable.py
deforest/tests/test_tags.py
deforest-0.4.0.dist-info/LICENSE
deforest-0.4.0.dist-info/METADATA
deforest-0.4.0.dist-info/WHEEL
deforest-0.4.0.dist-info/entry_points.txt
deforest-0.4.0.dist-info/top_level.txt
deforest-0.4.0.dist-info/RECORD
