Metadata-Version: 2.1
Name: deforest
Version: 0.4.0
Summary: Remove all x-amazon tags from your OAS3 specification
Home-page: https://github.com/hawry/deforest
Author: hawry
Author-email: hawry@hawry.net
License: UNKNOWN
Platform: UNKNOWN
Classifier: Programming Language :: Python :: 2.7
Classifier: License :: OSI Approved :: MIT License
Classifier: Operating System :: POSIX :: Linux
Classifier: Development Status :: 3 - Alpha
Requires-Dist: pyyaml (==5.1.1)
Requires-Dist: click (==7.1.1)
Requires-Dist: coloredlogs (==10.0)
